{"categories":[{"name":"Mediavida","icon":"Zap","items":[":psyduck:",":shutup:",":ninjaedit:",":f5:",":clint:",":buitre:"]},{"name":"Smileys y gente","icon":"Smile","items":[":+1:",":-1:",":adult:",":alien:",":angel:",":anger:",":anger_right:",":angry:",":anguished:",":astonished:",":athletic_shoe:",":baby:",":bath:",":bearded_person:",":bikini:",":billed_cap:",":black_heart:",":blond-haired_man:",":blond-haired_woman:",":blond_haired_person:",":blue_heart:",":blush:",":bomb:",":boom:",":boot:",":boy:",":brain:",":breast_feeding:",":bride_with_veil:",":broken_heart:",":bust_in_silhouette:",":busts_in_silhouette:",":call_me:",":child:",":clap:",":clown:",":coat:",":cold_sweat:",":confounded:",":confused:",":construction_worker:",":couple:",":couple_mm:",":couple_with_heart:",":couple_with_heart_woman_man:",":couple_ww:",":couplekiss:",":cowboy:",":crazy_face:",":crown:",":cry:",":crying_cat_face:",":cupid:",":dancer:",":dark_sunglasses:",":dash:",":detective:",":disappointed:",":disappointed_relieved:",":dizzy:",":dizzy_face:",":dress:",":drooling_face:",":ear:",":elf:",":exploding_head:",":expressionless:",":eye:",":eye_in_speech_bubble:",":eyeglasses:",":eyes:",":face_vomiting:",":face_with_hand_over_mouth:",":face_with_monocle:",":face_with_raised_eyebrow:",":face_with_symbols_over_mouth:",":fairy:",":family:",":family_man_boy:",":family_man_boy_boy:",":family_man_girl:",":family_man_girl_boy:",":family_man_girl_girl:",":family_man_woman_boy:",":family_mmb:",":family_mmbb:",":family_mmg:",":family_mmgb:",":family_mmgg:",":family_mwbb:",":family_mwg:",":family_mwgb:",":family_mwgg:",":family_woman_boy:",":family_woman_boy_boy:",":family_woman_girl:",":family_woman_girl_boy:",":family_woman_girl_girl:",":family_wwb:",":family_wwbb:",":family_wwg:",":family_wwgb:",":family_wwgg:",":fearful:",":fingers_crossed:",":fist:",":flushed:",":footprints:",":frowning:",":frowning2:",":gem:",":genie:",":ghost:",":gift_heart:",":girl:",":gloves:",":green_heart:",":grimacing:",":grin:",":grinning:",":guard:",":hand_splayed:",":handbag:",":handshake:",":head_bandage:",":hear_no_evil:",":heart:",":heart_decoration:",":heart_exclamation:",":heart_eyes:",":heart_eyes_cat:",":heartbeat:",":heartpulse:",":helmet_with_cross:",":high_heel:",":hole:",":horse_racing:",":hugging:",":hushed:",":imp:",":innocent:",":japanese_goblin:",":japanese_ogre:",":jeans:",":joy:",":joy_cat:",":kimono:",":kiss:",":kiss_mm:",":kiss_woman_man:",":kiss_ww:",":kissing:",":kissing_cat:",":kissing_closed_eyes:",":kissing_heart:",":kissing_smiling_eyes:",":laughing:",":left_facing_fist:",":levitate:",":lips:",":lipstick:",":love_letter:",":love_you_gesture:",":lying_face:",":mage:",":man:",":man_artist:",":man_astronaut:",":man_biking:",":man_bouncing_ball:",":man_bowing:",":man_cartwheeling:",":man_climbing:",":man_construction_worker:",":man_cook:",":man_dancing:",":man_detective:",":man_elf:",":man_facepalming:",":man_factory_worker:",":man_fairy:",":man_farmer:",":man_firefighter:",":man_frowning:",":man_genie:",":man_gesturing_no:",":man_gesturing_ok:",":man_getting_face_massage:",":man_getting_haircut:",":man_golfing:",":man_guard:",":man_health_worker:",":man_in_lotus_position:",":man_in_steamy_room:",":man_in_tuxedo:",":man_judge:",":man_juggling:",":man_lifting_weights:",":man_mage:",":man_mechanic:",":man_mountain_biking:",":man_office_worker:",":man_pilot:",":man_playing_handball:",":man_playing_water_polo:",":man_police_officer:",":man_pouting:",":man_raising_hand:",":man_rowing_boat:",":man_running:",":man_scientist:",":man_shrugging:",":man_singer:",":man_student:",":man_surfing:",":man_swimming:",":man_teacher:",":man_technologist:",":man_tipping_hand:",":man_vampire:",":man_walking:",":man_wearing_turban:",":man_with_chinese_cap:",":man_zombie:",":mans_shoe:",":mask:",":men_with_bunny_ears_partying:",":men_wrestling:",":mermaid:",":merman:",":merperson:",":metal:",":middle_finger:",":money_mouth:",":mortar_board:",":motorcycle:",":mrs_claus:",":muscle:",":nail_care:",":nauseated_face:",":necktie:",":nerd:",":neutral_face:",":no_mouth:",":nose:",":ok_hand:",":older_adult:",":older_man:",":older_woman:",":open_hands:",":open_mouth:",":orange_heart:",":palms_up_together:",":pensive:",":people_with_bunny_ears_partying:",":people_wrestling:",":persevere:",":person_biking:",":person_bouncing_ball:",":person_bowing:",":person_climbing:",":person_doing_cartwheel:",":person_facepalming:",":person_fencing:",":person_frowning:",":person_gesturing_no:",":person_gesturing_ok:",":person_getting_haircut:",":person_getting_massage:",":person_golfing:",":person_in_lotus_position:",":person_in_steamy_room:",":person_juggling:",":person_lifting_weights:",":person_mountain_biking:",":person_playing_handball:",":person_playing_water_polo:",":person_pouting:",":person_raising_hand:",":person_rowing_boat:",":person_running:",":person_shrugging:",":person_surfing:",":person_swimming:",":person_tipping_hand:",":person_walking:",":person_wearing_turban:",":point_down:",":point_left:",":point_right:",":point_up:",":point_up_2:",":police_officer:",":poop:",":pouch:",":pouting_cat:",":pray:",":prayer_beads:",":pregnant_woman:",":prince:",":princess:",":punch:",":purple_heart:",":purse:",":race_car:",":rage:",":raised_back_of_hand:",":raised_hand:",":raised_hands:",":relaxed:",":relieved:",":revolving_hearts:",":right_facing_fist:",":ring:",":robot:",":rofl:",":rolling_eyes:",":sandal:",":santa:",":scarf:",":school_satchel:",":scream:",":scream_cat:",":see_no_evil:",":selfie:",":shirt:",":shopping_bags:",":shushing_face:",":skier:",":skull:",":skull_crossbones:",":sleeping:",":sleeping_accommodation:",":sleepy:",":slight_frown:",":slight_smile:",":smile:",":smile_cat:",":smiley:",":smiley_cat:",":smiling_imp:",":smirk:",":smirk_cat:",":sneezing_face:",":snowboarder:",":sob:",":socks:",":space_invader:",":sparkling_heart:",":speak_no_evil:",":speaking_head:",":speech_balloon:",":speech_left:",":star_struck:",":stuck_out_tongue:",":stuck_out_tongue_closed_eyes:",":stuck_out_tongue_winking_eye:",":sunglasses:",":sweat:",":sweat_drops:",":sweat_smile:",":thermometer_face:",":thinking:",":thought_balloon:",":tired_face:",":tongue:",":tophat:",":triumph:",":two_hearts:",":two_men_holding_hands:",":two_women_holding_hands:",":unamused:",":upside_down:",":v:",":vampire:",":vulcan:",":wave:",":weary:",":wink:",":woman:",":woman_artist:",":woman_astronaut:",":woman_biking:",":woman_bouncing_ball:",":woman_bowing:",":woman_cartwheeling:",":woman_climbing:",":woman_construction_worker:",":woman_cook:",":woman_detective:",":woman_elf:",":woman_facepalming:",":woman_factory_worker:",":woman_fairy:",":woman_farmer:",":woman_firefighter:",":woman_frowning:",":woman_genie:",":woman_gesturing_no:",":woman_gesturing_ok:",":woman_getting_face_massage:",":woman_getting_haircut:",":woman_golfing:",":woman_guard:",":woman_health_worker:",":woman_in_lotus_position:",":woman_in_steamy_room:",":woman_judge:",":woman_juggling:",":woman_lifting_weights:",":woman_mage:",":woman_mechanic:",":woman_mountain_biking:",":woman_office_worker:",":woman_pilot:",":woman_playing_handball:",":woman_playing_water_polo:",":woman_police_officer:",":woman_pouting:",":woman_raising_hand:",":woman_rowing_boat:",":woman_running:",":woman_scientist:",":woman_shrugging:",":woman_singer:",":woman_student:",":woman_surfing:",":woman_swimming:",":woman_teacher:",":woman_technologist:",":woman_tipping_hand:",":woman_vampire:",":woman_walking:",":woman_wearing_turban:",":woman_with_headscarf:",":woman_zombie:",":womans_clothes:",":womans_hat:",":women_with_bunny_ears_partying:",":women_wrestling:",":worried:",":writing_hand:",":yellow_heart:",":yum:",":zipper_mouth:",":zombie:",":zzz:"]},{"name":"Símbolos","icon":"Hash","items":[":100:",":1234:",":a:",":ab:",":abc:",":abcd:",":accept:",":aquarius:",":aries:",":arrow_backward:",":arrow_double_down:",":arrow_double_up:",":arrow_down:",":arrow_down_small:",":arrow_forward:",":arrow_heading_down:",":arrow_heading_up:",":arrow_left:",":arrow_lower_left:",":arrow_lower_right:",":arrow_right:",":arrow_right_hook:",":arrow_up:",":arrow_up_down:",":arrow_up_small:",":arrow_upper_left:",":arrow_upper_right:",":arrows_clockwise:",":arrows_counterclockwise:",":asterisk:",":atm:",":atom:",":b:",":baby_symbol:",":back:",":baggage_claim:",":ballot_box_with_check:",":bangbang:",":beginner:",":biohazard:",":black_circle:",":black_large_square:",":black_medium_small_square:",":black_medium_square:",":black_small_square:",":black_square_button:",":blue_circle:",":cancer:",":capital_abcd:",":capricorn:",":children_crossing:",":cinema:",":cl:",":congratulations:",":cool:",":copyright:",":cross:",":curly_loop:",":customs:",":diamond_shape_with_a_dot_inside:",":do_not_litter:",":eight:",":eight_pointed_black_star:",":eight_spoked_asterisk:",":eject:",":end:",":exclamation:",":fast_forward:",":female_sign:",":five:",":fleur-de-lis:",":four:",":free:",":gemini:",":grey_exclamation:",":grey_question:",":hash:",":heavy_check_mark:",":heavy_division_sign:",":heavy_minus_sign:",":heavy_multiplication_x:",":heavy_plus_sign:",":high_brightness:",":id:",":ideograph_advantage:",":information_source:",":interrobang:",":keycap_ten:",":koko:",":large_blue_diamond:",":large_orange_diamond:",":left_luggage:",":left_right_arrow:",":leftwards_arrow_with_hook:",":leo:",":libra:",":loop:",":low_brightness:",":m:",":male_sign:",":medical_symbol:",":menorah:",":mens:",":mobile_phone_off:",":name_badge:",":negative_squared_cross_mark:",":new:",":ng:",":nine:",":no_bicycles:",":no_entry:",":no_entry_sign:",":no_mobile_phones:",":no_pedestrians:",":no_smoking:",":non-potable_water:",":o:",":o2:",":ok:",":om_symbol:",":on:",":one:",":ophiuchus:",":orthodox_cross:",":parking:",":part_alternation_mark:",":passport_control:",":pause_button:",":peace:",":pisces:",":place_of_worship:",":play_pause:",":potable_water:",":put_litter_in_its_place:",":question:",":radio_button:",":radioactive:",":record_button:",":recycle:",":red_circle:",":registered:",":repeat:",":repeat_one:",":restroom:",":rewind:",":sa:",":sagittarius:",":scorpius:",":secret:",":seven:",":signal_strength:",":six:",":six_pointed_star:",":small_blue_diamond:",":small_orange_diamond:",":small_red_triangle:",":small_red_triangle_down:",":soon:",":sos:",":sparkle:",":star_and_crescent:",":star_of_david:",":stop_button:",":symbols:",":taurus:",":three:",":tm:",":top:",":track_next:",":track_previous:",":trident:",":twisted_rightwards_arrows:",":two:",":u5272:",":u5408:",":u55b6:",":u6307:",":u6708:",":u6709:",":u6e80:",":u7121:",":u7533:",":u7981:",":u7a7a:",":underage:",":up:",":vibration_mode:",":virgo:",":vs:",":warning:",":wavy_dash:",":wc:",":wheel_of_dharma:",":wheelchair:",":white_check_mark:",":white_circle:",":white_large_square:",":white_medium_small_square:",":white_medium_square:",":white_small_square:",":white_square_button:",":womens:",":x:",":yin_yang:",":zero:"]},{"name":"Actividades","icon":"Trophy","items":[":8ball:",":badminton:",":balloon:",":bamboo:",":baseball:",":basketball:",":black_joker:",":bowling:",":boxing_glove:",":christmas_tree:",":clubs:",":confetti_ball:",":cricket_game:",":curling_stone:",":dart:",":diamonds:",":dolls:",":field_hockey:",":fireworks:",":first_place:",":fishing_pole_and_fish:",":flags:",":flower_playing_cards:",":football:",":game_die:",":gift:",":goal:",":golf:",":hearts:",":hockey:",":ice_skate:",":jack_o_lantern:",":joystick:",":mahjong:",":martial_arts_uniform:",":medal:",":military_medal:",":ping_pong:",":reminder_ribbon:",":ribbon:",":rice_scene:",":rugby_football:",":running_shirt_with_sash:",":second_place:",":ski:",":sled:",":soccer:",":spades:",":sparkler:",":sparkles:",":tada:",":tanabata_tree:",":tennis:",":third_place:",":ticket:",":tickets:",":trophy:",":video_game:",":volleyball:",":wind_chime:"]},{"name":"Viajes y lugares","icon":"Map","items":[":aerial_tramway:",":airplane:",":airplane_arriving:",":airplane_departure:",":airplane_small:",":alarm_clock:",":ambulance:",":anchor:",":art:",":articulated_lorry:",":bank:",":barber:",":bathtub:",":beach:",":beach_umbrella:",":bed:",":bellhop:",":bike:",":blue_car:",":bridge_at_night:",":bullettrain_front:",":bullettrain_side:",":bus:",":busstop:",":camping:",":canoe:",":carousel_horse:",":church:",":circus_tent:",":city_dusk:",":city_sunset:",":cityscape:",":classical_building:",":clock:",":clock1:",":clock10:",":clock1030:",":clock11:",":clock1130:",":clock12:",":clock1230:",":clock130:",":clock2:",":clock230:",":clock3:",":clock330:",":clock4:",":clock430:",":clock5:",":clock530:",":clock6:",":clock630:",":clock7:",":clock730:",":clock8:",":clock830:",":clock9:",":clock930:",":closed_umbrella:",":cloud:",":cloud_lightning:",":cloud_rain:",":cloud_snow:",":cloud_tornado:",":comet:",":construction:",":construction_site:",":convenience_store:",":couch:",":crescent_moon:",":cruise_ship:",":cyclone:",":department_store:",":desert:",":door:",":droplet:",":earth_africa:",":earth_americas:",":earth_asia:",":european_castle:",":european_post_office:",":factory:",":ferris_wheel:",":ferry:",":fire:",":fire_engine:",":first_quarter_moon:",":first_quarter_moon_with_face:",":flying_saucer:",":fog:",":foggy:",":fountain:",":frame_photo:",":fuelpump:",":full_moon:",":full_moon_with_face:",":globe_with_meridians:",":helicopter:",":homes:",":hospital:",":hotel:",":hotsprings:",":hourglass:",":hourglass_flowing_sand:",":house:",":house_abandoned:",":house_with_garden:",":island:",":japan:",":japanese_castle:",":kaaba:",":last_quarter_moon:",":last_quarter_moon_with_face:",":light_rail:",":love_hotel:",":map:",":metro:",":milky_way:",":minibus:",":monorail:",":mosque:",":motor_scooter:",":motorboat:",":motorway:",":mount_fuji:",":mountain:",":mountain_cableway:",":mountain_railway:",":mountain_snow:",":new_moon:",":new_moon_with_face:",":night_with_stars:",":ocean:",":octagonal_sign:",":office:",":oncoming_automobile:",":oncoming_bus:",":oncoming_police_car:",":oncoming_taxi:",":park:",":partly_sunny:",":performing_arts:",":police_car:",":post_office:",":railway_car:",":railway_track:",":rainbow:",":red_car:",":rocket:",":roller_coaster:",":rotating_light:",":sailboat:",":satellite_orbital:",":school:",":scooter:",":seat:",":shinto_shrine:",":ship:",":shower:",":slot_machine:",":snowflake:",":snowman:",":snowman2:",":speedboat:",":stadium:",":star:",":star2:",":stars:",":station:",":statue_of_liberty:",":steam_locomotive:",":stopwatch:",":sun_with_face:",":sunny:",":sunrise:",":sunrise_over_mountains:",":suspension_railway:",":synagogue:",":taxi:",":tent:",":thermometer:",":thunder_cloud_rain:",":timer:",":toilet:",":tokyo_tower:",":tractor:",":traffic_light:",":train:",":train2:",":tram:",":trolleybus:",":truck:",":umbrella:",":umbrella2:",":vertical_traffic_light:",":volcano:",":waning_crescent_moon:",":waning_gibbous_moon:",":watch:",":waxing_crescent_moon:",":waxing_gibbous_moon:",":wedding:",":white_sun_cloud:",":white_sun_rain_cloud:",":white_sun_small_cloud:",":wind_blowing_face:",":zap:"]},{"name":"Objetos","icon":"Lightbulb","items":[":alembic:",":ballot_box:",":bar_chart:",":battery:",":bell:",":black_nib:",":blue_book:",":book:",":bookmark:",":bookmark_tabs:",":books:",":bow_and_arrow:",":briefcase:",":bulb:",":calendar:",":calendar_spiral:",":calling:",":camera:",":camera_with_flash:",":candle:",":card_box:",":card_index:",":cd:",":chains:",":chart:",":chart_with_downwards_trend:",":chart_with_upwards_trend:",":clapper:",":clipboard:",":closed_book:",":closed_lock_with_key:",":coffin:",":compression:",":computer:",":control_knobs:",":crayon:",":credit_card:",":crossed_swords:",":crystal_ball:",":currency_exchange:",":dagger:",":date:",":desktop:",":dividers:",":dollar:",":drum:",":dvd:",":e-mail:",":electric_plug:",":envelope:",":envelope_with_arrow:",":euro:",":fax:",":file_cabinet:",":file_folder:",":film_frames:",":flashlight:",":floppy_disk:",":gear:",":green_book:",":guitar:",":gun:",":hammer:",":hammer_pick:",":headphones:",":heavy_dollar_sign:",":inbox_tray:",":incoming_envelope:",":iphone:",":izakaya_lantern:",":key:",":key2:",":keyboard:",":label:",":ledger:",":level_slider:",":link:",":lock:",":lock_with_ink_pen:",":loud_sound:",":loudspeaker:",":mag:",":mag_right:",":mailbox:",":mailbox_closed:",":mailbox_with_mail:",":mailbox_with_no_mail:",":mega:",":microphone:",":microphone2:",":microscope:",":minidisc:",":money_with_wings:",":moneybag:",":mouse_three_button:",":movie_camera:",":moyai:",":musical_keyboard:",":musical_note:",":musical_score:",":mute:",":newspaper:",":newspaper2:",":no_bell:",":notebook:",":notebook_with_decorative_cover:",":notepad_spiral:",":notes:",":nut_and_bolt:",":oil:",":open_file_folder:",":orange_book:",":outbox_tray:",":package:",":page_facing_up:",":page_with_curl:",":pager:",":paintbrush:",":paperclip:",":paperclips:",":pen_ballpoint:",":pen_fountain:",":pencil:",":pencil2:",":pick:",":pill:",":postal_horn:",":postbox:",":pound:",":printer:",":projector:",":pushpin:",":radio:",":round_pushpin:",":satellite:",":saxophone:",":scales:",":scissors:",":scroll:",":shield:",":shopping_cart:",":smoking:",":sound:",":speaker:",":straight_ruler:",":syringe:",":telephone:",":telephone_receiver:",":telescope:",":tools:",":trackball:",":triangular_ruler:",":trumpet:",":tv:",":unlock:",":urn:",":vhs:",":video_camera:",":violin:",":wastebasket:",":wrench:",":yen:"]},{"name":"Comida y bebida","icon":"Coffee","items":[":amphora:",":apple:",":avocado:",":baby_bottle:",":bacon:",":banana:",":beer:",":beers:",":bento:",":birthday:",":bowl_with_spoon:",":bread:",":broccoli:",":burrito:",":cake:",":candy:",":canned_food:",":carrot:",":champagne:",":champagne_glass:",":cheese:",":cherries:",":chestnut:",":chocolate_bar:",":chopsticks:",":cocktail:",":coconut:",":coffee:",":cookie:",":cooking:",":corn:",":croissant:",":cucumber:",":cup_with_straw:",":curry:",":custard:",":cut_of_meat:",":dango:",":doughnut:",":dumpling:",":egg:",":eggplant:",":fish_cake:",":fork_and_knife:",":fork_knife_plate:",":fortune_cookie:",":french_bread:",":fried_shrimp:",":fries:",":grapes:",":green_apple:",":hamburger:",":honey_pot:",":hot_pepper:",":hotdog:",":ice_cream:",":icecream:",":kiwi:",":knife:",":lemon:",":lollipop:",":meat_on_bone:",":melon:",":milk:",":mushroom:",":oden:",":pancakes:",":peach:",":peanuts:",":pear:",":pie:",":pineapple:",":pizza:",":popcorn:",":potato:",":poultry_leg:",":pretzel:",":ramen:",":rice:",":rice_ball:",":rice_cracker:",":sake:",":salad:",":sandwich:",":shallow_pan_of_food:",":shaved_ice:",":spaghetti:",":spoon:",":stew:",":strawberry:",":stuffed_flatbread:",":sushi:",":sweet_potato:",":taco:",":takeout_box:",":tangerine:",":tea:",":tomato:",":tropical_drink:",":tumbler_glass:",":watermelon:",":wine_glass:"]},{"name":"Animales y naturaleza","icon":"Cat","items":[":ant:",":baby_chick:",":bat:",":bear:",":bee:",":beetle:",":bird:",":blossom:",":blowfish:",":boar:",":bouquet:",":bug:",":butterfly:",":cactus:",":camel:",":cat:",":cat2:",":cherry_blossom:",":chicken:",":chipmunk:",":cow:",":cow2:",":crab:",":cricket:",":crocodile:",":deciduous_tree:",":deer:",":dog:",":dog2:",":dolphin:",":dove:",":dragon:",":dragon_face:",":dromedary_camel:",":duck:",":eagle:",":ear_of_rice:",":elephant:",":evergreen_tree:",":fallen_leaf:",":feet:",":fish:",":four_leaf_clover:",":fox:",":frog:",":giraffe:",":goat:",":gorilla:",":hamster:",":hatched_chick:",":hatching_chick:",":hedgehog:",":herb:",":hibiscus:",":horse:",":koala:",":leaves:",":leopard:",":lion_face:",":lizard:",":maple_leaf:",":monkey:",":monkey_face:",":mouse:",":mouse2:",":octopus:",":owl:",":ox:",":palm_tree:",":panda_face:",":penguin:",":pig:",":pig2:",":pig_nose:",":poodle:",":rabbit:",":rabbit2:",":racehorse:",":ram:",":rat:",":rhino:",":rooster:",":rose:",":rosette:",":sauropod:",":scorpion:",":seedling:",":shamrock:",":shark:",":sheep:",":shell:",":shrimp:",":snail:",":snake:",":spider:",":spider_web:",":squid:",":sunflower:",":t_rex:",":tiger:",":tiger2:",":tropical_fish:",":tulip:",":turkey:",":turtle:",":unicorn:",":water_buffalo:",":whale:",":whale2:",":white_flower:",":wilted_rose:",":wolf:",":zebra:"]},{"name":"Banderas","icon":"Flag","items":[":checkered_flag:",":crossed_flags:",":england:",":flag_ac:",":flag_ad:",":flag_ae:",":flag_af:",":flag_ag:",":flag_ai:",":flag_al:",":flag_am:",":flag_ao:",":flag_aq:",":flag_ar:",":flag_as:",":flag_at:",":flag_au:",":flag_aw:",":flag_ax:",":flag_az:",":flag_ba:",":flag_bb:",":flag_bd:",":flag_be:",":flag_bf:",":flag_bg:",":flag_bh:",":flag_bi:",":flag_bj:",":flag_bl:",":flag_black:",":flag_bm:",":flag_bn:",":flag_bo:",":flag_bq:",":flag_br:",":flag_bs:",":flag_bt:",":flag_bv:",":flag_bw:",":flag_by:",":flag_bz:",":flag_ca:",":flag_cc:",":flag_cd:",":flag_cf:",":flag_cg:",":flag_ch:",":flag_ci:",":flag_ck:",":flag_cl:",":flag_cm:",":flag_cn:",":flag_co:",":flag_cp:",":flag_cr:",":flag_cu:",":flag_cv:",":flag_cw:",":flag_cx:",":flag_cy:",":flag_cz:",":flag_de:",":flag_dg:",":flag_dj:",":flag_dk:",":flag_dm:",":flag_do:",":flag_dz:",":flag_ea:",":flag_ec:",":flag_ee:",":flag_eg:",":flag_eh:",":flag_er:",":flag_es:",":flag_et:",":flag_eu:",":flag_fi:",":flag_fj:",":flag_fk:",":flag_fm:",":flag_fo:",":flag_fr:",":flag_ga:",":flag_gb:",":flag_gd:",":flag_ge:",":flag_gf:",":flag_gg:",":flag_gh:",":flag_gi:",":flag_gl:",":flag_gm:",":flag_gn:",":flag_gp:",":flag_gq:",":flag_gr:",":flag_gs:",":flag_gt:",":flag_gu:",":flag_gw:",":flag_gy:",":flag_hk:",":flag_hm:",":flag_hn:",":flag_hr:",":flag_ht:",":flag_hu:",":flag_ic:",":flag_id:",":flag_ie:",":flag_il:",":flag_im:",":flag_in:",":flag_io:",":flag_iq:",":flag_ir:",":flag_is:",":flag_it:",":flag_je:",":flag_jm:",":flag_jo:",":flag_jp:",":flag_ke:",":flag_kg:",":flag_kh:",":flag_ki:",":flag_km:",":flag_kn:",":flag_kp:",":flag_kr:",":flag_kw:",":flag_ky:",":flag_kz:",":flag_la:",":flag_lb:",":flag_lc:",":flag_li:",":flag_lk:",":flag_lr:",":flag_ls:",":flag_lt:",":flag_lu:",":flag_lv:",":flag_ly:",":flag_ma:",":flag_mc:",":flag_md:",":flag_me:",":flag_mf:",":flag_mg:",":flag_mh:",":flag_mk:",":flag_ml:",":flag_mm:",":flag_mn:",":flag_mo:",":flag_mp:",":flag_mq:",":flag_mr:",":flag_ms:",":flag_mt:",":flag_mu:",":flag_mv:",":flag_mw:",":flag_mx:",":flag_my:",":flag_mz:",":flag_na:",":flag_nc:",":flag_ne:",":flag_nf:",":flag_ng:",":flag_ni:",":flag_nl:",":flag_no:",":flag_np:",":flag_nr:",":flag_nu:",":flag_nz:",":flag_om:",":flag_pa:",":flag_pe:",":flag_pf:",":flag_pg:",":flag_ph:",":flag_pk:",":flag_pl:",":flag_pm:",":flag_pn:",":flag_pr:",":flag_ps:",":flag_pt:",":flag_pw:",":flag_py:",":flag_qa:",":flag_re:",":flag_ro:",":flag_rs:",":flag_ru:",":flag_rw:",":flag_sa:",":flag_sb:",":flag_sc:",":flag_sd:",":flag_se:",":flag_sg:",":flag_sh:",":flag_si:",":flag_sj:",":flag_sk:",":flag_sl:",":flag_sm:",":flag_sn:",":flag_so:",":flag_sr:",":flag_ss:",":flag_st:",":flag_sv:",":flag_sx:",":flag_sy:",":flag_sz:",":flag_ta:",":flag_tc:",":flag_td:",":flag_tf:",":flag_tg:",":flag_th:",":flag_tj:",":flag_tk:",":flag_tl:",":flag_tm:",":flag_tn:",":flag_to:",":flag_tr:",":flag_tt:",":flag_tv:",":flag_tw:",":flag_tz:",":flag_ua:",":flag_ug:",":flag_um:",":flag_us:",":flag_uy:",":flag_uz:",":flag_va:",":flag_vc:",":flag_ve:",":flag_vg:",":flag_vi:",":flag_vn:",":flag_vu:",":flag_wf:",":flag_white:",":flag_ws:",":flag_xk:",":flag_ye:",":flag_yt:",":flag_za:",":flag_zm:",":flag_zw:",":rainbow_flag:",":scotland:",":triangular_flag_on_post:",":united_nations:",":wales:"]}],"emojis":{":psyduck:":"psyduck.gif",":shutup:":"fry.png",":ninjaedit:":"ninjaedit.gif",":f5:":"f5.gif",":clint:":"clint.gif",":buitre:":"buitre.gif",":+1:":"u/1f44d.png",":-1:":"u/1f44e.png",":adult:":"u/1f9d1.png",":alien:":"u/1f47d.png",":angel:":"u/1f47c.png",":anger:":"u/1f4a2.png",":anger_right:":"u/1f5ef.png",":angry:":"u/1f620.png",":anguished:":"u/1f627.png",":astonished:":"u/1f632.png",":athletic_shoe:":"u/1f45f.png",":baby:":"u/1f476.png",":bath:":"u/1f6c0.png",":bearded_person:":"u/1f9d4.png",":bikini:":"u/1f459.png",":billed_cap:":"u/1f9e2.png",":black_heart:":"u/1f5a4.png",":blond-haired_man:":"u/1f471-2642.png",":blond-haired_woman:":"u/1f471-2640.png",":blond_haired_person:":"u/1f471.png",":blue_heart:":"u/1f499.png",":blush:":"u/1f60a.png",":bomb:":"u/1f4a3.png",":boom:":"u/1f4a5.png",":boot:":"u/1f462.png",":boy:":"u/1f466.png",":brain:":"u/1f9e0.png",":breast_feeding:":"u/1f931.png",":bride_with_veil:":"u/1f470.png",":broken_heart:":"u/1f494.png",":bust_in_silhouette:":"u/1f464.png",":busts_in_silhouette:":"u/1f465.png",":call_me:":"u/1f919.png",":child:":"u/1f9d2.png",":clap:":"u/1f44f.png",":clown:":"u/1f921.png",":coat:":"u/1f9e5.png",":cold_sweat:":"u/1f630.png",":confounded:":"u/1f616.png",":confused:":"u/1f615.png",":construction_worker:":"u/1f477.png",":couple:":"u/1f46b.png",":couple_mm:":"u/1f468-2764-1f468.png",":couple_with_heart:":"u/1f491.png",":couple_with_heart_woman_man:":"u/1f469-2764-1f468.png",":couple_ww:":"u/1f469-2764-1f469.png",":couplekiss:":"u/1f48f.png",":cowboy:":"u/1f920.png",":crazy_face:":"u/1f92a.png",":crown:":"u/1f451.png",":cry:":"u/1f622.png",":crying_cat_face:":"u/1f63f.png",":cupid:":"u/1f498.png",":dancer:":"u/1f483.png",":dark_sunglasses:":"u/1f576.png",":dash:":"u/1f4a8.png",":detective:":"u/1f575.png",":disappointed:":"u/1f61e.png",":disappointed_relieved:":"u/1f625.png",":dizzy:":"u/1f4ab.png",":dizzy_face:":"u/1f635.png",":dress:":"u/1f457.png",":drooling_face:":"u/1f924.png",":ear:":"u/1f442.png",":elf:":"u/1f9dd.png",":exploding_head:":"u/1f92f.png",":expressionless:":"u/1f611.png",":eye:":"u/1f441.png",":eye_in_speech_bubble:":"u/1f441-1f5e8.png",":eyeglasses:":"u/1f453.png",":eyes:":"u/1f440.png",":face_vomiting:":"u/1f92e.png",":face_with_hand_over_mouth:":"u/1f92d.png",":face_with_monocle:":"u/1f9d0.png",":face_with_raised_eyebrow:":"u/1f928.png",":face_with_symbols_over_mouth:":"u/1f92c.png",":fairy:":"u/1f9da.png",":family:":"u/1f46a.png",":family_man_boy:":"u/1f468-1f466.png",":family_man_boy_boy:":"u/1f468-1f466-1f466.png",":family_man_girl:":"u/1f468-1f467.png",":family_man_girl_boy:":"u/1f468-1f467-1f466.png",":family_man_girl_girl:":"u/1f468-1f467-1f467.png",":family_man_woman_boy:":"u/1f468-1f469-1f466.png",":family_mmb:":"u/1f468-1f468-1f466.png",":family_mmbb:":"u/1f468-1f468-1f466-1f466.png",":family_mmg:":"u/1f468-1f468-1f467.png",":family_mmgb:":"u/1f468-1f468-1f467-1f466.png",":family_mmgg:":"u/1f468-1f468-1f467-1f467.png",":family_mwbb:":"u/1f468-1f469-1f466-1f466.png",":family_mwg:":"u/1f468-1f469-1f467.png",":family_mwgb:":"u/1f468-1f469-1f467-1f466.png",":family_mwgg:":"u/1f468-1f469-1f467-1f467.png",":family_woman_boy:":"u/1f469-1f466.png",":family_woman_boy_boy:":"u/1f469-1f466-1f466.png",":family_woman_girl:":"u/1f469-1f467.png",":family_woman_girl_boy:":"u/1f469-1f467-1f466.png",":family_woman_girl_girl:":"u/1f469-1f467-1f467.png",":family_wwb:":"u/1f469-1f469-1f466.png",":family_wwbb:":"u/1f469-1f469-1f466-1f466.png",":family_wwg:":"u/1f469-1f469-1f467.png",":family_wwgb:":"u/1f469-1f469-1f467-1f466.png",":family_wwgg:":"u/1f469-1f469-1f467-1f467.png",":fearful:":"u/1f628.png",":fingers_crossed:":"u/1f91e.png",":fist:":"u/270a.png",":flushed:":"u/1f633.png",":footprints:":"u/1f463.png",":frowning:":"u/1f626.png",":frowning2:":"u/2639.png",":gem:":"u/1f48e.png",":genie:":"u/1f9de.png",":ghost:":"u/1f47b.png",":gift_heart:":"u/1f49d.png",":girl:":"u/1f467.png",":gloves:":"u/1f9e4.png",":green_heart:":"u/1f49a.png",":grimacing:":"u/1f62c.png",":grin:":"u/1f601.png",":grinning:":"u/1f600.png",":guard:":"u/1f482.png",":hand_splayed:":"u/1f590.png",":handbag:":"u/1f45c.png",":handshake:":"u/1f91d.png",":head_bandage:":"u/1f915.png",":hear_no_evil:":"u/1f649.png",":heart:":"u/2764.png",":heart_decoration:":"u/1f49f.png",":heart_exclamation:":"u/2763.png",":heart_eyes:":"u/1f60d.png",":heart_eyes_cat:":"u/1f63b.png",":heartbeat:":"u/1f493.png",":heartpulse:":"u/1f497.png",":helmet_with_cross:":"u/26d1.png",":high_heel:":"u/1f460.png",":hole:":"u/1f573.png",":horse_racing:":"u/1f3c7.png",":hugging:":"u/1f917.png",":hushed:":"u/1f62f.png",":imp:":"u/1f47f.png",":innocent:":"u/1f607.png",":japanese_goblin:":"u/1f47a.png",":japanese_ogre:":"u/1f479.png",":jeans:":"u/1f456.png",":joy:":"u/1f602.png",":joy_cat:":"u/1f639.png",":kimono:":"u/1f458.png",":kiss:":"u/1f48b.png",":kiss_mm:":"u/1f468-2764-1f48b-1f468.png",":kiss_woman_man:":"u/1f469-2764-1f48b-1f468.png",":kiss_ww:":"u/1f469-2764-1f48b-1f469.png",":kissing:":"u/1f617.png",":kissing_cat:":"u/1f63d.png",":kissing_closed_eyes:":"u/1f61a.png",":kissing_heart:":"u/1f618.png",":kissing_smiling_eyes:":"u/1f619.png",":laughing:":"u/1f606.png",":left_facing_fist:":"u/1f91b.png",":levitate:":"u/1f574.png",":lips:":"u/1f444.png",":lipstick:":"u/1f484.png",":love_letter:":"u/1f48c.png",":love_you_gesture:":"u/1f91f.png",":lying_face:":"u/1f925.png",":mage:":"u/1f9d9.png",":man:":"u/1f468.png",":man_artist:":"u/1f468-1f3a8.png",":man_astronaut:":"u/1f468-1f680.png",":man_biking:":"u/1f6b4-2642.png",":man_bouncing_ball:":"u/26f9-2642.png",":man_bowing:":"u/1f647-2642.png",":man_cartwheeling:":"u/1f938-2642.png",":man_climbing:":"u/1f9d7-2642.png",":man_construction_worker:":"u/1f477-2642.png",":man_cook:":"u/1f468-1f373.png",":man_dancing:":"u/1f57a.png",":man_detective:":"u/1f575-2642.png",":man_elf:":"u/1f9dd-2642.png",":man_facepalming:":"u/1f926-2642.png",":man_factory_worker:":"u/1f468-1f3ed.png",":man_fairy:":"u/1f9da-2642.png",":man_farmer:":"u/1f468-1f33e.png",":man_firefighter:":"u/1f468-1f692.png",":man_frowning:":"u/1f64d-2642.png",":man_genie:":"u/1f9de-2642.png",":man_gesturing_no:":"u/1f645-2642.png",":man_gesturing_ok:":"u/1f646-2642.png",":man_getting_face_massage:":"u/1f486-2642.png",":man_getting_haircut:":"u/1f487-2642.png",":man_golfing:":"u/1f3cc-2642.png",":man_guard:":"u/1f482-2642.png",":man_health_worker:":"u/1f468-2695.png",":man_in_lotus_position:":"u/1f9d8-2642.png",":man_in_steamy_room:":"u/1f9d6-2642.png",":man_in_tuxedo:":"u/1f935.png",":man_judge:":"u/1f468-2696.png",":man_juggling:":"u/1f939-2642.png",":man_lifting_weights:":"u/1f3cb-2642.png",":man_mage:":"u/1f9d9-2642.png",":man_mechanic:":"u/1f468-1f527.png",":man_mountain_biking:":"u/1f6b5-2642.png",":man_office_worker:":"u/1f468-1f4bc.png",":man_pilot:":"u/1f468-2708.png",":man_playing_handball:":"u/1f93e-2642.png",":man_playing_water_polo:":"u/1f93d-2642.png",":man_police_officer:":"u/1f46e-2642.png",":man_pouting:":"u/1f64e-2642.png",":man_raising_hand:":"u/1f64b-2642.png",":man_rowing_boat:":"u/1f6a3-2642.png",":man_running:":"u/1f3c3-2642.png",":man_scientist:":"u/1f468-1f52c.png",":man_shrugging:":"u/1f937-2642.png",":man_singer:":"u/1f468-1f3a4.png",":man_student:":"u/1f468-1f393.png",":man_surfing:":"u/1f3c4-2642.png",":man_swimming:":"u/1f3ca-2642.png",":man_teacher:":"u/1f468-1f3eb.png",":man_technologist:":"u/1f468-1f4bb.png",":man_tipping_hand:":"u/1f481-2642.png",":man_vampire:":"u/1f9db-2642.png",":man_walking:":"u/1f6b6-2642.png",":man_wearing_turban:":"u/1f473-2642.png",":man_with_chinese_cap:":"u/1f472.png",":man_zombie:":"u/1f9df-2642.png",":mans_shoe:":"u/1f45e.png",":mask:":"u/1f637.png",":men_with_bunny_ears_partying:":"u/1f46f-2642.png",":men_wrestling:":"u/1f93c-2642.png",":mermaid:":"u/1f9dc-2640.png",":merman:":"u/1f9dc-2642.png",":merperson:":"u/1f9dc.png",":metal:":"u/1f918.png",":middle_finger:":"u/1f595.png",":money_mouth:":"u/1f911.png",":mortar_board:":"u/1f393.png",":motorcycle:":"u/1f3cd.png",":mrs_claus:":"u/1f936.png",":muscle:":"u/1f4aa.png",":nail_care:":"u/1f485.png",":nauseated_face:":"u/1f922.png",":necktie:":"u/1f454.png",":nerd:":"u/1f913.png",":neutral_face:":"u/1f610.png",":no_mouth:":"u/1f636.png",":nose:":"u/1f443.png",":ok_hand:":"u/1f44c.png",":older_adult:":"u/1f9d3.png",":older_man:":"u/1f474.png",":older_woman:":"u/1f475.png",":open_hands:":"u/1f450.png",":open_mouth:":"u/1f62e.png",":orange_heart:":"u/1f9e1.png",":palms_up_together:":"u/1f932.png",":pensive:":"u/1f614.png",":people_with_bunny_ears_partying:":"u/1f46f.png",":people_wrestling:":"u/1f93c.png",":persevere:":"u/1f623.png",":person_biking:":"u/1f6b4.png",":person_bouncing_ball:":"u/26f9.png",":person_bowing:":"u/1f647.png",":person_climbing:":"u/1f9d7.png",":person_doing_cartwheel:":"u/1f938.png",":person_facepalming:":"u/1f926.png",":person_fencing:":"u/1f93a.png",":person_frowning:":"u/1f64d.png",":person_gesturing_no:":"u/1f645.png",":person_gesturing_ok:":"u/1f646.png",":person_getting_haircut:":"u/1f487.png",":person_getting_massage:":"u/1f486.png",":person_golfing:":"u/1f3cc.png",":person_in_lotus_position:":"u/1f9d8.png",":person_in_steamy_room:":"u/1f9d6.png",":person_juggling:":"u/1f939.png",":person_lifting_weights:":"u/1f3cb.png",":person_mountain_biking:":"u/1f6b5.png",":person_playing_handball:":"u/1f93e.png",":person_playing_water_polo:":"u/1f93d.png",":person_pouting:":"u/1f64e.png",":person_raising_hand:":"u/1f64b.png",":person_rowing_boat:":"u/1f6a3.png",":person_running:":"u/1f3c3.png",":person_shrugging:":"u/1f937.png",":person_surfing:":"u/1f3c4.png",":person_swimming:":"u/1f3ca.png",":person_tipping_hand:":"u/1f481.png",":person_walking:":"u/1f6b6.png",":person_wearing_turban:":"u/1f473.png",":point_down:":"u/1f447.png",":point_left:":"u/1f448.png",":point_right:":"u/1f449.png",":point_up:":"u/261d.png",":point_up_2:":"u/1f446.png",":police_officer:":"u/1f46e.png",":poop:":"u/1f4a9.png",":pouch:":"u/1f45d.png",":pouting_cat:":"u/1f63e.png",":pray:":"u/1f64f.png",":prayer_beads:":"u/1f4ff.png",":pregnant_woman:":"u/1f930.png",":prince:":"u/1f934.png",":princess:":"u/1f478.png",":punch:":"u/1f44a.png",":purple_heart:":"u/1f49c.png",":purse:":"u/1f45b.png",":race_car:":"u/1f3ce.png",":rage:":"u/1f621.png",":raised_back_of_hand:":"u/1f91a.png",":raised_hand:":"u/270b.png",":raised_hands:":"u/1f64c.png",":relaxed:":"u/263a.png",":relieved:":"u/1f60c.png",":revolving_hearts:":"u/1f49e.png",":right_facing_fist:":"u/1f91c.png",":ring:":"u/1f48d.png",":robot:":"u/1f916.png",":rofl:":"u/1f923.png",":rolling_eyes:":"u/1f644.png",":sandal:":"u/1f461.png",":santa:":"u/1f385.png",":scarf:":"u/1f9e3.png",":school_satchel:":"u/1f392.png",":scream:":"u/1f631.png",":scream_cat:":"u/1f640.png",":see_no_evil:":"u/1f648.png",":selfie:":"u/1f933.png",":shirt:":"u/1f455.png",":shopping_bags:":"u/1f6cd.png",":shushing_face:":"u/1f92b.png",":skier:":"u/26f7.png",":skull:":"u/1f480.png",":skull_crossbones:":"u/2620.png",":sleeping:":"u/1f634.png",":sleeping_accommodation:":"u/1f6cc.png",":sleepy:":"u/1f62a.png",":slight_frown:":"u/1f641.png",":slight_smile:":"u/1f642.png",":smile:":"u/1f604.png",":smile_cat:":"u/1f638.png",":smiley:":"u/1f603.png",":smiley_cat:":"u/1f63a.png",":smiling_imp:":"u/1f608.png",":smirk:":"u/1f60f.png",":smirk_cat:":"u/1f63c.png",":sneezing_face:":"u/1f927.png",":snowboarder:":"u/1f3c2.png",":sob:":"u/1f62d.png",":socks:":"u/1f9e6.png",":space_invader:":"u/1f47e.png",":sparkling_heart:":"u/1f496.png",":speak_no_evil:":"u/1f64a.png",":speaking_head:":"u/1f5e3.png",":speech_balloon:":"u/1f4ac.png",":speech_left:":"u/1f5e8.png",":star_struck:":"u/1f929.png",":stuck_out_tongue:":"u/1f61b.png",":stuck_out_tongue_closed_eyes:":"u/1f61d.png",":stuck_out_tongue_winking_eye:":"u/1f61c.png",":sunglasses:":"u/1f60e.png",":sweat:":"u/1f613.png",":sweat_drops:":"u/1f4a6.png",":sweat_smile:":"u/1f605.png",":thermometer_face:":"u/1f912.png",":thinking:":"u/1f914.png",":thought_balloon:":"u/1f4ad.png",":tired_face:":"u/1f62b.png",":tongue:":"u/1f445.png",":tophat:":"u/1f3a9.png",":triumph:":"u/1f624.png",":two_hearts:":"u/1f495.png",":two_men_holding_hands:":"u/1f46c.png",":two_women_holding_hands:":"u/1f46d.png",":unamused:":"u/1f612.png",":upside_down:":"u/1f643.png",":v:":"u/270c.png",":vampire:":"u/1f9db.png",":vulcan:":"u/1f596.png",":wave:":"u/1f44b.png",":weary:":"u/1f629.png",":wink:":"u/1f609.png",":woman:":"u/1f469.png",":woman_artist:":"u/1f469-1f3a8.png",":woman_astronaut:":"u/1f469-1f680.png",":woman_biking:":"u/1f6b4-2640.png",":woman_bouncing_ball:":"u/26f9-2640.png",":woman_bowing:":"u/1f647-2640.png",":woman_cartwheeling:":"u/1f938-2640.png",":woman_climbing:":"u/1f9d7-2640.png",":woman_construction_worker:":"u/1f477-2640.png",":woman_cook:":"u/1f469-1f373.png",":woman_detective:":"u/1f575-2640.png",":woman_elf:":"u/1f9dd-2640.png",":woman_facepalming:":"u/1f926-2640.png",":woman_factory_worker:":"u/1f469-1f3ed.png",":woman_fairy:":"u/1f9da-2640.png",":woman_farmer:":"u/1f469-1f33e.png",":woman_firefighter:":"u/1f469-1f692.png",":woman_frowning:":"u/1f64d-2640.png",":woman_genie:":"u/1f9de-2640.png",":woman_gesturing_no:":"u/1f645-2640.png",":woman_gesturing_ok:":"u/1f646-2640.png",":woman_getting_face_massage:":"u/1f486-2640.png",":woman_getting_haircut:":"u/1f487-2640.png",":woman_golfing:":"u/1f3cc-2640.png",":woman_guard:":"u/1f482-2640.png",":woman_health_worker:":"u/1f469-2695.png",":woman_in_lotus_position:":"u/1f9d8-2640.png",":woman_in_steamy_room:":"u/1f9d6-2640.png",":woman_judge:":"u/1f469-2696.png",":woman_juggling:":"u/1f939-2640.png",":woman_lifting_weights:":"u/1f3cb-2640.png",":woman_mage:":"u/1f9d9-2640.png",":woman_mechanic:":"u/1f469-1f527.png",":woman_mountain_biking:":"u/1f6b5-2640.png",":woman_office_worker:":"u/1f469-1f4bc.png",":woman_pilot:":"u/1f469-2708.png",":woman_playing_handball:":"u/1f93e-2640.png",":woman_playing_water_polo:":"u/1f93d-2640.png",":woman_police_officer:":"u/1f46e-2640.png",":woman_pouting:":"u/1f64e-2640.png",":woman_raising_hand:":"u/1f64b-2640.png",":woman_rowing_boat:":"u/1f6a3-2640.png",":woman_running:":"u/1f3c3-2640.png",":woman_scientist:":"u/1f469-1f52c.png",":woman_shrugging:":"u/1f937-2640.png",":woman_singer:":"u/1f469-1f3a4.png",":woman_student:":"u/1f469-1f393.png",":woman_surfing:":"u/1f3c4-2640.png",":woman_swimming:":"u/1f3ca-2640.png",":woman_teacher:":"u/1f469-1f3eb.png",":woman_technologist:":"u/1f469-1f4bb.png",":woman_tipping_hand:":"u/1f481-2640.png",":woman_vampire:":"u/1f9db-2640.png",":woman_walking:":"u/1f6b6-2640.png",":woman_wearing_turban:":"u/1f473-2640.png",":woman_with_headscarf:":"u/1f9d5.png",":woman_zombie:":"u/1f9df-2640.png",":womans_clothes:":"u/1f45a.png",":womans_hat:":"u/1f452.png",":women_with_bunny_ears_partying:":"u/1f46f-2640.png",":women_wrestling:":"u/1f93c-2640.png",":worried:":"u/1f61f.png",":writing_hand:":"u/270d.png",":yellow_heart:":"u/1f49b.png",":yum:":"u/1f60b.png",":zipper_mouth:":"u/1f910.png",":zombie:":"u/1f9df.png",":zzz:":"u/1f4a4.png",":100:":"u/1f4af.png",":1234:":"u/1f522.png",":a:":"u/1f170.png",":ab:":"u/1f18e.png",":abc:":"u/1f524.png",":abcd:":"u/1f521.png",":accept:":"u/1f251.png",":aquarius:":"u/2652.png",":aries:":"u/2648.png",":arrow_backward:":"u/25c0.png",":arrow_double_down:":"u/23ec.png",":arrow_double_up:":"u/23eb.png",":arrow_down:":"u/2b07.png",":arrow_down_small:":"u/1f53d.png",":arrow_forward:":"u/25b6.png",":arrow_heading_down:":"u/2935.png",":arrow_heading_up:":"u/2934.png",":arrow_left:":"u/2b05.png",":arrow_lower_left:":"u/2199.png",":arrow_lower_right:":"u/2198.png",":arrow_right:":"u/27a1.png",":arrow_right_hook:":"u/21aa.png",":arrow_up:":"u/2b06.png",":arrow_up_down:":"u/2195.png",":arrow_up_small:":"u/1f53c.png",":arrow_upper_left:":"u/2196.png",":arrow_upper_right:":"u/2197.png",":arrows_clockwise:":"u/1f503.png",":arrows_counterclockwise:":"u/1f504.png",":asterisk:":"u/002a-20e3.png",":atm:":"u/1f3e7.png",":atom:":"u/269b.png",":b:":"u/1f171.png",":baby_symbol:":"u/1f6bc.png",":back:":"u/1f519.png",":baggage_claim:":"u/1f6c4.png",":ballot_box_with_check:":"u/2611.png",":bangbang:":"u/203c.png",":beginner:":"u/1f530.png",":biohazard:":"u/2623.png",":black_circle:":"u/26ab.png",":black_large_square:":"u/2b1b.png",":black_medium_small_square:":"u/25fe.png",":black_medium_square:":"u/25fc.png",":black_small_square:":"u/25aa.png",":black_square_button:":"u/1f532.png",":blue_circle:":"u/1f535.png",":cancer:":"u/264b.png",":capital_abcd:":"u/1f520.png",":capricorn:":"u/2651.png",":children_crossing:":"u/1f6b8.png",":cinema:":"u/1f3a6.png",":cl:":"u/1f191.png",":congratulations:":"u/3297.png",":cool:":"u/1f192.png",":copyright:":"u/00a9.png",":cross:":"u/271d.png",":curly_loop:":"u/27b0.png",":customs:":"u/1f6c3.png",":diamond_shape_with_a_dot_inside:":"u/1f4a0.png",":do_not_litter:":"u/1f6af.png",":eight:":"u/0038-20e3.png",":eight_pointed_black_star:":"u/2734.png",":eight_spoked_asterisk:":"u/2733.png",":eject:":"u/23cf.png",":end:":"u/1f51a.png",":exclamation:":"u/2757.png",":fast_forward:":"u/23e9.png",":female_sign:":"u/2640.png",":five:":"u/0035-20e3.png",":fleur-de-lis:":"u/269c.png",":four:":"u/0034-20e3.png",":free:":"u/1f193.png",":gemini:":"u/264a.png",":grey_exclamation:":"u/2755.png",":grey_question:":"u/2754.png",":hash:":"u/0023-20e3.png",":heavy_check_mark:":"u/2714.png",":heavy_division_sign:":"u/2797.png",":heavy_minus_sign:":"u/2796.png",":heavy_multiplication_x:":"u/2716.png",":heavy_plus_sign:":"u/2795.png",":high_brightness:":"u/1f506.png",":id:":"u/1f194.png",":ideograph_advantage:":"u/1f250.png",":information_source:":"u/2139.png",":interrobang:":"u/2049.png",":keycap_ten:":"u/1f51f.png",":koko:":"u/1f201.png",":large_blue_diamond:":"u/1f537.png",":large_orange_diamond:":"u/1f536.png",":left_luggage:":"u/1f6c5.png",":left_right_arrow:":"u/2194.png",":leftwards_arrow_with_hook:":"u/21a9.png",":leo:":"u/264c.png",":libra:":"u/264e.png",":loop:":"u/27bf.png",":low_brightness:":"u/1f505.png",":m:":"u/24c2.png",":male_sign:":"u/2642.png",":medical_symbol:":"u/2695.png",":menorah:":"u/1f54e.png",":mens:":"u/1f6b9.png",":mobile_phone_off:":"u/1f4f4.png",":name_badge:":"u/1f4db.png",":negative_squared_cross_mark:":"u/274e.png",":new:":"u/1f195.png",":ng:":"u/1f196.png",":nine:":"u/0039-20e3.png",":no_bicycles:":"u/1f6b3.png",":no_entry:":"u/26d4.png",":no_entry_sign:":"u/1f6ab.png",":no_mobile_phones:":"u/1f4f5.png",":no_pedestrians:":"u/1f6b7.png",":no_smoking:":"u/1f6ad.png",":non-potable_water:":"u/1f6b1.png",":o:":"u/2b55.png",":o2:":"u/1f17e.png",":ok:":"u/1f197.png",":om_symbol:":"u/1f549.png",":on:":"u/1f51b.png",":one:":"u/0031-20e3.png",":ophiuchus:":"u/26ce.png",":orthodox_cross:":"u/2626.png",":parking:":"u/1f17f.png",":part_alternation_mark:":"u/303d.png",":passport_control:":"u/1f6c2.png",":pause_button:":"u/23f8.png",":peace:":"u/262e.png",":pisces:":"u/2653.png",":place_of_worship:":"u/1f6d0.png",":play_pause:":"u/23ef.png",":potable_water:":"u/1f6b0.png",":put_litter_in_its_place:":"u/1f6ae.png",":question:":"u/2753.png",":radio_button:":"u/1f518.png",":radioactive:":"u/2622.png",":record_button:":"u/23fa.png",":recycle:":"u/267b.png",":red_circle:":"u/1f534.png",":registered:":"u/00ae.png",":repeat:":"u/1f501.png",":repeat_one:":"u/1f502.png",":restroom:":"u/1f6bb.png",":rewind:":"u/23ea.png",":sa:":"u/1f202.png",":sagittarius:":"u/2650.png",":scorpius:":"u/264f.png",":secret:":"u/3299.png",":seven:":"u/0037-20e3.png",":signal_strength:":"u/1f4f6.png",":six:":"u/0036-20e3.png",":six_pointed_star:":"u/1f52f.png",":small_blue_diamond:":"u/1f539.png",":small_orange_diamond:":"u/1f538.png",":small_red_triangle:":"u/1f53a.png",":small_red_triangle_down:":"u/1f53b.png",":soon:":"u/1f51c.png",":sos:":"u/1f198.png",":sparkle:":"u/2747.png",":star_and_crescent:":"u/262a.png",":star_of_david:":"u/2721.png",":stop_button:":"u/23f9.png",":symbols:":"u/1f523.png",":taurus:":"u/2649.png",":three:":"u/0033-20e3.png",":tm:":"u/2122.png",":top:":"u/1f51d.png",":track_next:":"u/23ed.png",":track_previous:":"u/23ee.png",":trident:":"u/1f531.png",":twisted_rightwards_arrows:":"u/1f500.png",":two:":"u/0032-20e3.png",":u5272:":"u/1f239.png",":u5408:":"u/1f234.png",":u55b6:":"u/1f23a.png",":u6307:":"u/1f22f.png",":u6708:":"u/1f237.png",":u6709:":"u/1f236.png",":u6e80:":"u/1f235.png",":u7121:":"u/1f21a.png",":u7533:":"u/1f238.png",":u7981:":"u/1f232.png",":u7a7a:":"u/1f233.png",":underage:":"u/1f51e.png",":up:":"u/1f199.png",":vibration_mode:":"u/1f4f3.png",":virgo:":"u/264d.png",":vs:":"u/1f19a.png",":warning:":"u/26a0.png",":wavy_dash:":"u/3030.png",":wc:":"u/1f6be.png",":wheel_of_dharma:":"u/2638.png",":wheelchair:":"u/267f.png",":white_check_mark:":"u/2705.png",":white_circle:":"u/26aa.png",":white_large_square:":"u/2b1c.png",":white_medium_small_square:":"u/25fd.png",":white_medium_square:":"u/25fb.png",":white_small_square:":"u/25ab.png",":white_square_button:":"u/1f533.png",":womens:":"u/1f6ba.png",":x:":"u/274c.png",":yin_yang:":"u/262f.png",":zero:":"u/0030-20e3.png",":8ball:":"u/1f3b1.png",":badminton:":"u/1f3f8.png",":balloon:":"u/1f388.png",":bamboo:":"u/1f38d.png",":baseball:":"u/26be.png",":basketball:":"u/1f3c0.png",":black_joker:":"u/1f0cf.png",":bowling:":"u/1f3b3.png",":boxing_glove:":"u/1f94a.png",":christmas_tree:":"u/1f384.png",":clubs:":"u/2663.png",":confetti_ball:":"u/1f38a.png",":cricket_game:":"u/1f3cf.png",":curling_stone:":"u/1f94c.png",":dart:":"u/1f3af.png",":diamonds:":"u/2666.png",":dolls:":"u/1f38e.png",":field_hockey:":"u/1f3d1.png",":fireworks:":"u/1f386.png",":first_place:":"u/1f947.png",":fishing_pole_and_fish:":"u/1f3a3.png",":flags:":"u/1f38f.png",":flower_playing_cards:":"u/1f3b4.png",":football:":"u/1f3c8.png",":game_die:":"u/1f3b2.png",":gift:":"u/1f381.png",":goal:":"u/1f945.png",":golf:":"u/26f3.png",":hearts:":"u/2665.png",":hockey:":"u/1f3d2.png",":ice_skate:":"u/26f8.png",":jack_o_lantern:":"u/1f383.png",":joystick:":"u/1f579.png",":mahjong:":"u/1f004.png",":martial_arts_uniform:":"u/1f94b.png",":medal:":"u/1f3c5.png",":military_medal:":"u/1f396.png",":ping_pong:":"u/1f3d3.png",":reminder_ribbon:":"u/1f397.png",":ribbon:":"u/1f380.png",":rice_scene:":"u/1f391.png",":rugby_football:":"u/1f3c9.png",":running_shirt_with_sash:":"u/1f3bd.png",":second_place:":"u/1f948.png",":ski:":"u/1f3bf.png",":sled:":"u/1f6f7.png",":soccer:":"u/26bd.png",":spades:":"u/2660.png",":sparkler:":"u/1f387.png",":sparkles:":"u/2728.png",":tada:":"u/1f389.png",":tanabata_tree:":"u/1f38b.png",":tennis:":"u/1f3be.png",":third_place:":"u/1f949.png",":ticket:":"u/1f3ab.png",":tickets:":"u/1f39f.png",":trophy:":"u/1f3c6.png",":video_game:":"u/1f3ae.png",":volleyball:":"u/1f3d0.png",":wind_chime:":"u/1f390.png",":aerial_tramway:":"u/1f6a1.png",":airplane:":"u/2708.png",":airplane_arriving:":"u/1f6ec.png",":airplane_departure:":"u/1f6eb.png",":airplane_small:":"u/1f6e9.png",":alarm_clock:":"u/23f0.png",":ambulance:":"u/1f691.png",":anchor:":"u/2693.png",":art:":"u/1f3a8.png",":articulated_lorry:":"u/1f69b.png",":bank:":"u/1f3e6.png",":barber:":"u/1f488.png",":bathtub:":"u/1f6c1.png",":beach:":"u/1f3d6.png",":beach_umbrella:":"u/26f1.png",":bed:":"u/1f6cf.png",":bellhop:":"u/1f6ce.png",":bike:":"u/1f6b2.png",":blue_car:":"u/1f699.png",":bridge_at_night:":"u/1f309.png",":bullettrain_front:":"u/1f685.png",":bullettrain_side:":"u/1f684.png",":bus:":"u/1f68c.png",":busstop:":"u/1f68f.png",":camping:":"u/1f3d5.png",":canoe:":"u/1f6f6.png",":carousel_horse:":"u/1f3a0.png",":church:":"u/26ea.png",":circus_tent:":"u/1f3aa.png",":city_dusk:":"u/1f306.png",":city_sunset:":"u/1f307.png",":cityscape:":"u/1f3d9.png",":classical_building:":"u/1f3db.png",":clock:":"u/1f570.png",":clock1:":"u/1f550.png",":clock10:":"u/1f559.png",":clock1030:":"u/1f565.png",":clock11:":"u/1f55a.png",":clock1130:":"u/1f566.png",":clock12:":"u/1f55b.png",":clock1230:":"u/1f567.png",":clock130:":"u/1f55c.png",":clock2:":"u/1f551.png",":clock230:":"u/1f55d.png",":clock3:":"u/1f552.png",":clock330:":"u/1f55e.png",":clock4:":"u/1f553.png",":clock430:":"u/1f55f.png",":clock5:":"u/1f554.png",":clock530:":"u/1f560.png",":clock6:":"u/1f555.png",":clock630:":"u/1f561.png",":clock7:":"u/1f556.png",":clock730:":"u/1f562.png",":clock8:":"u/1f557.png",":clock830:":"u/1f563.png",":clock9:":"u/1f558.png",":clock930:":"u/1f564.png",":closed_umbrella:":"u/1f302.png",":cloud:":"u/2601.png",":cloud_lightning:":"u/1f329.png",":cloud_rain:":"u/1f327.png",":cloud_snow:":"u/1f328.png",":cloud_tornado:":"u/1f32a.png",":comet:":"u/2604.png",":construction:":"u/1f6a7.png",":construction_site:":"u/1f3d7.png",":convenience_store:":"u/1f3ea.png",":couch:":"u/1f6cb.png",":crescent_moon:":"u/1f319.png",":cruise_ship:":"u/1f6f3.png",":cyclone:":"u/1f300.png",":department_store:":"u/1f3ec.png",":desert:":"u/1f3dc.png",":door:":"u/1f6aa.png",":droplet:":"u/1f4a7.png",":earth_africa:":"u/1f30d.png",":earth_americas:":"u/1f30e.png",":earth_asia:":"u/1f30f.png",":european_castle:":"u/1f3f0.png",":european_post_office:":"u/1f3e4.png",":factory:":"u/1f3ed.png",":ferris_wheel:":"u/1f3a1.png",":ferry:":"u/26f4.png",":fire:":"u/1f525.png",":fire_engine:":"u/1f692.png",":first_quarter_moon:":"u/1f313.png",":first_quarter_moon_with_face:":"u/1f31b.png",":flying_saucer:":"u/1f6f8.png",":fog:":"u/1f32b.png",":foggy:":"u/1f301.png",":fountain:":"u/26f2.png",":frame_photo:":"u/1f5bc.png",":fuelpump:":"u/26fd.png",":full_moon:":"u/1f315.png",":full_moon_with_face:":"u/1f31d.png",":globe_with_meridians:":"u/1f310.png",":helicopter:":"u/1f681.png",":homes:":"u/1f3d8.png",":hospital:":"u/1f3e5.png",":hotel:":"u/1f3e8.png",":hotsprings:":"u/2668.png",":hourglass:":"u/231b.png",":hourglass_flowing_sand:":"u/23f3.png",":house:":"u/1f3e0.png",":house_abandoned:":"u/1f3da.png",":house_with_garden:":"u/1f3e1.png",":island:":"u/1f3dd.png",":japan:":"u/1f5fe.png",":japanese_castle:":"u/1f3ef.png",":kaaba:":"u/1f54b.png",":last_quarter_moon:":"u/1f317.png",":last_quarter_moon_with_face:":"u/1f31c.png",":light_rail:":"u/1f688.png",":love_hotel:":"u/1f3e9.png",":map:":"u/1f5fa.png",":metro:":"u/1f687.png",":milky_way:":"u/1f30c.png",":minibus:":"u/1f690.png",":monorail:":"u/1f69d.png",":mosque:":"u/1f54c.png",":motor_scooter:":"u/1f6f5.png",":motorboat:":"u/1f6e5.png",":motorway:":"u/1f6e3.png",":mount_fuji:":"u/1f5fb.png",":mountain:":"u/26f0.png",":mountain_cableway:":"u/1f6a0.png",":mountain_railway:":"u/1f69e.png",":mountain_snow:":"u/1f3d4.png",":new_moon:":"u/1f311.png",":new_moon_with_face:":"u/1f31a.png",":night_with_stars:":"u/1f303.png",":ocean:":"u/1f30a.png",":octagonal_sign:":"u/1f6d1.png",":office:":"u/1f3e2.png",":oncoming_automobile:":"u/1f698.png",":oncoming_bus:":"u/1f68d.png",":oncoming_police_car:":"u/1f694.png",":oncoming_taxi:":"u/1f696.png",":park:":"u/1f3de.png",":partly_sunny:":"u/26c5.png",":performing_arts:":"u/1f3ad.png",":police_car:":"u/1f693.png",":post_office:":"u/1f3e3.png",":railway_car:":"u/1f683.png",":railway_track:":"u/1f6e4.png",":rainbow:":"u/1f308.png",":red_car:":"u/1f697.png",":rocket:":"u/1f680.png",":roller_coaster:":"u/1f3a2.png",":rotating_light:":"u/1f6a8.png",":sailboat:":"u/26f5.png",":satellite_orbital:":"u/1f6f0.png",":school:":"u/1f3eb.png",":scooter:":"u/1f6f4.png",":seat:":"u/1f4ba.png",":shinto_shrine:":"u/26e9.png",":ship:":"u/1f6a2.png",":shower:":"u/1f6bf.png",":slot_machine:":"u/1f3b0.png",":snowflake:":"u/2744.png",":snowman:":"u/26c4.png",":snowman2:":"u/2603.png",":speedboat:":"u/1f6a4.png",":stadium:":"u/1f3df.png",":star:":"u/2b50.png",":star2:":"u/1f31f.png",":stars:":"u/1f320.png",":station:":"u/1f689.png",":statue_of_liberty:":"u/1f5fd.png",":steam_locomotive:":"u/1f682.png",":stopwatch:":"u/23f1.png",":sun_with_face:":"u/1f31e.png",":sunny:":"u/2600.png",":sunrise:":"u/1f305.png",":sunrise_over_mountains:":"u/1f304.png",":suspension_railway:":"u/1f69f.png",":synagogue:":"u/1f54d.png",":taxi:":"u/1f695.png",":tent:":"u/26fa.png",":thermometer:":"u/1f321.png",":thunder_cloud_rain:":"u/26c8.png",":timer:":"u/23f2.png",":toilet:":"u/1f6bd.png",":tokyo_tower:":"u/1f5fc.png",":tractor:":"u/1f69c.png",":traffic_light:":"u/1f6a5.png",":train:":"u/1f68b.png",":train2:":"u/1f686.png",":tram:":"u/1f68a.png",":trolleybus:":"u/1f68e.png",":truck:":"u/1f69a.png",":umbrella:":"u/2614.png",":umbrella2:":"u/2602.png",":vertical_traffic_light:":"u/1f6a6.png",":volcano:":"u/1f30b.png",":waning_crescent_moon:":"u/1f318.png",":waning_gibbous_moon:":"u/1f316.png",":watch:":"u/231a.png",":waxing_crescent_moon:":"u/1f312.png",":waxing_gibbous_moon:":"u/1f314.png",":wedding:":"u/1f492.png",":white_sun_cloud:":"u/1f325.png",":white_sun_rain_cloud:":"u/1f326.png",":white_sun_small_cloud:":"u/1f324.png",":wind_blowing_face:":"u/1f32c.png",":zap:":"u/26a1.png",":alembic:":"u/2697.png",":ballot_box:":"u/1f5f3.png",":bar_chart:":"u/1f4ca.png",":battery:":"u/1f50b.png",":bell:":"u/1f514.png",":black_nib:":"u/2712.png",":blue_book:":"u/1f4d8.png",":book:":"u/1f4d6.png",":bookmark:":"u/1f516.png",":bookmark_tabs:":"u/1f4d1.png",":books:":"u/1f4da.png",":bow_and_arrow:":"u/1f3f9.png",":briefcase:":"u/1f4bc.png",":bulb:":"u/1f4a1.png",":calendar:":"u/1f4c6.png",":calendar_spiral:":"u/1f5d3.png",":calling:":"u/1f4f2.png",":camera:":"u/1f4f7.png",":camera_with_flash:":"u/1f4f8.png",":candle:":"u/1f56f.png",":card_box:":"u/1f5c3.png",":card_index:":"u/1f4c7.png",":cd:":"u/1f4bf.png",":chains:":"u/26d3.png",":chart:":"u/1f4b9.png",":chart_with_downwards_trend:":"u/1f4c9.png",":chart_with_upwards_trend:":"u/1f4c8.png",":clapper:":"u/1f3ac.png",":clipboard:":"u/1f4cb.png",":closed_book:":"u/1f4d5.png",":closed_lock_with_key:":"u/1f510.png",":coffin:":"u/26b0.png",":compression:":"u/1f5dc.png",":computer:":"u/1f4bb.png",":control_knobs:":"u/1f39b.png",":crayon:":"u/1f58d.png",":credit_card:":"u/1f4b3.png",":crossed_swords:":"u/2694.png",":crystal_ball:":"u/1f52e.png",":currency_exchange:":"u/1f4b1.png",":dagger:":"u/1f5e1.png",":date:":"u/1f4c5.png",":desktop:":"u/1f5a5.png",":dividers:":"u/1f5c2.png",":dollar:":"u/1f4b5.png",":drum:":"u/1f941.png",":dvd:":"u/1f4c0.png",":e-mail:":"u/1f4e7.png",":electric_plug:":"u/1f50c.png",":envelope:":"u/2709.png",":envelope_with_arrow:":"u/1f4e9.png",":euro:":"u/1f4b6.png",":fax:":"u/1f4e0.png",":file_cabinet:":"u/1f5c4.png",":file_folder:":"u/1f4c1.png",":film_frames:":"u/1f39e.png",":flashlight:":"u/1f526.png",":floppy_disk:":"u/1f4be.png",":gear:":"u/2699.png",":green_book:":"u/1f4d7.png",":guitar:":"u/1f3b8.png",":gun:":"u/1f52b.png",":hammer:":"u/1f528.png",":hammer_pick:":"u/2692.png",":headphones:":"u/1f3a7.png",":heavy_dollar_sign:":"u/1f4b2.png",":inbox_tray:":"u/1f4e5.png",":incoming_envelope:":"u/1f4e8.png",":iphone:":"u/1f4f1.png",":izakaya_lantern:":"u/1f3ee.png",":key:":"u/1f511.png",":key2:":"u/1f5dd.png",":keyboard:":"u/2328.png",":label:":"u/1f3f7.png",":ledger:":"u/1f4d2.png",":level_slider:":"u/1f39a.png",":link:":"u/1f517.png",":lock:":"u/1f512.png",":lock_with_ink_pen:":"u/1f50f.png",":loud_sound:":"u/1f50a.png",":loudspeaker:":"u/1f4e2.png",":mag:":"u/1f50d.png",":mag_right:":"u/1f50e.png",":mailbox:":"u/1f4eb.png",":mailbox_closed:":"u/1f4ea.png",":mailbox_with_mail:":"u/1f4ec.png",":mailbox_with_no_mail:":"u/1f4ed.png",":mega:":"u/1f4e3.png",":microphone:":"u/1f3a4.png",":microphone2:":"u/1f399.png",":microscope:":"u/1f52c.png",":minidisc:":"u/1f4bd.png",":money_with_wings:":"u/1f4b8.png",":moneybag:":"u/1f4b0.png",":mouse_three_button:":"u/1f5b1.png",":movie_camera:":"u/1f3a5.png",":moyai:":"u/1f5ff.png",":musical_keyboard:":"u/1f3b9.png",":musical_note:":"u/1f3b5.png",":musical_score:":"u/1f3bc.png",":mute:":"u/1f507.png",":newspaper:":"u/1f4f0.png",":newspaper2:":"u/1f5de.png",":no_bell:":"u/1f515.png",":notebook:":"u/1f4d3.png",":notebook_with_decorative_cover:":"u/1f4d4.png",":notepad_spiral:":"u/1f5d2.png",":notes:":"u/1f3b6.png",":nut_and_bolt:":"u/1f529.png",":oil:":"u/1f6e2.png",":open_file_folder:":"u/1f4c2.png",":orange_book:":"u/1f4d9.png",":outbox_tray:":"u/1f4e4.png",":package:":"u/1f4e6.png",":page_facing_up:":"u/1f4c4.png",":page_with_curl:":"u/1f4c3.png",":pager:":"u/1f4df.png",":paintbrush:":"u/1f58c.png",":paperclip:":"u/1f4ce.png",":paperclips:":"u/1f587.png",":pen_ballpoint:":"u/1f58a.png",":pen_fountain:":"u/1f58b.png",":pencil:":"u/1f4dd.png",":pencil2:":"u/270f.png",":pick:":"u/26cf.png",":pill:":"u/1f48a.png",":postal_horn:":"u/1f4ef.png",":postbox:":"u/1f4ee.png",":pound:":"u/1f4b7.png",":printer:":"u/1f5a8.png",":projector:":"u/1f4fd.png",":pushpin:":"u/1f4cc.png",":radio:":"u/1f4fb.png",":round_pushpin:":"u/1f4cd.png",":satellite:":"u/1f4e1.png",":saxophone:":"u/1f3b7.png",":scales:":"u/2696.png",":scissors:":"u/2702.png",":scroll:":"u/1f4dc.png",":shield:":"u/1f6e1.png",":shopping_cart:":"u/1f6d2.png",":smoking:":"u/1f6ac.png",":sound:":"u/1f509.png",":speaker:":"u/1f508.png",":straight_ruler:":"u/1f4cf.png",":syringe:":"u/1f489.png",":telephone:":"u/260e.png",":telephone_receiver:":"u/1f4de.png",":telescope:":"u/1f52d.png",":tools:":"u/1f6e0.png",":trackball:":"u/1f5b2.png",":triangular_ruler:":"u/1f4d0.png",":trumpet:":"u/1f3ba.png",":tv:":"u/1f4fa.png",":unlock:":"u/1f513.png",":urn:":"u/26b1.png",":vhs:":"u/1f4fc.png",":video_camera:":"u/1f4f9.png",":violin:":"u/1f3bb.png",":wastebasket:":"u/1f5d1.png",":wrench:":"u/1f527.png",":yen:":"u/1f4b4.png",":amphora:":"u/1f3fa.png",":apple:":"u/1f34e.png",":avocado:":"u/1f951.png",":baby_bottle:":"u/1f37c.png",":bacon:":"u/1f953.png",":banana:":"u/1f34c.png",":beer:":"u/1f37a.png",":beers:":"u/1f37b.png",":bento:":"u/1f371.png",":birthday:":"u/1f382.png",":bowl_with_spoon:":"u/1f963.png",":bread:":"u/1f35e.png",":broccoli:":"u/1f966.png",":burrito:":"u/1f32f.png",":cake:":"u/1f370.png",":candy:":"u/1f36c.png",":canned_food:":"u/1f96b.png",":carrot:":"u/1f955.png",":champagne:":"u/1f37e.png",":champagne_glass:":"u/1f942.png",":cheese:":"u/1f9c0.png",":cherries:":"u/1f352.png",":chestnut:":"u/1f330.png",":chocolate_bar:":"u/1f36b.png",":chopsticks:":"u/1f962.png",":cocktail:":"u/1f378.png",":coconut:":"u/1f965.png",":coffee:":"u/2615.png",":cookie:":"u/1f36a.png",":cooking:":"u/1f373.png",":corn:":"u/1f33d.png",":croissant:":"u/1f950.png",":cucumber:":"u/1f952.png",":cup_with_straw:":"u/1f964.png",":curry:":"u/1f35b.png",":custard:":"u/1f36e.png",":cut_of_meat:":"u/1f969.png",":dango:":"u/1f361.png",":doughnut:":"u/1f369.png",":dumpling:":"u/1f95f.png",":egg:":"u/1f95a.png",":eggplant:":"u/1f346.png",":fish_cake:":"u/1f365.png",":fork_and_knife:":"u/1f374.png",":fork_knife_plate:":"u/1f37d.png",":fortune_cookie:":"u/1f960.png",":french_bread:":"u/1f956.png",":fried_shrimp:":"u/1f364.png",":fries:":"u/1f35f.png",":grapes:":"u/1f347.png",":green_apple:":"u/1f34f.png",":hamburger:":"u/1f354.png",":honey_pot:":"u/1f36f.png",":hot_pepper:":"u/1f336.png",":hotdog:":"u/1f32d.png",":ice_cream:":"u/1f368.png",":icecream:":"u/1f366.png",":kiwi:":"u/1f95d.png",":knife:":"u/1f52a.png",":lemon:":"u/1f34b.png",":lollipop:":"u/1f36d.png",":meat_on_bone:":"u/1f356.png",":melon:":"u/1f348.png",":milk:":"u/1f95b.png",":mushroom:":"u/1f344.png",":oden:":"u/1f362.png",":pancakes:":"u/1f95e.png",":peach:":"u/1f351.png",":peanuts:":"u/1f95c.png",":pear:":"u/1f350.png",":pie:":"u/1f967.png",":pineapple:":"u/1f34d.png",":pizza:":"u/1f355.png",":popcorn:":"u/1f37f.png",":potato:":"u/1f954.png",":poultry_leg:":"u/1f357.png",":pretzel:":"u/1f968.png",":ramen:":"u/1f35c.png",":rice:":"u/1f35a.png",":rice_ball:":"u/1f359.png",":rice_cracker:":"u/1f358.png",":sake:":"u/1f376.png",":salad:":"u/1f957.png",":sandwich:":"u/1f96a.png",":shallow_pan_of_food:":"u/1f958.png",":shaved_ice:":"u/1f367.png",":spaghetti:":"u/1f35d.png",":spoon:":"u/1f944.png",":stew:":"u/1f372.png",":strawberry:":"u/1f353.png",":stuffed_flatbread:":"u/1f959.png",":sushi:":"u/1f363.png",":sweet_potato:":"u/1f360.png",":taco:":"u/1f32e.png",":takeout_box:":"u/1f961.png",":tangerine:":"u/1f34a.png",":tea:":"u/1f375.png",":tomato:":"u/1f345.png",":tropical_drink:":"u/1f379.png",":tumbler_glass:":"u/1f943.png",":watermelon:":"u/1f349.png",":wine_glass:":"u/1f377.png",":ant:":"u/1f41c.png",":baby_chick:":"u/1f424.png",":bat:":"u/1f987.png",":bear:":"u/1f43b.png",":bee:":"u/1f41d.png",":beetle:":"u/1f41e.png",":bird:":"u/1f426.png",":blossom:":"u/1f33c.png",":blowfish:":"u/1f421.png",":boar:":"u/1f417.png",":bouquet:":"u/1f490.png",":bug:":"u/1f41b.png",":butterfly:":"u/1f98b.png",":cactus:":"u/1f335.png",":camel:":"u/1f42b.png",":cat:":"u/1f431.png",":cat2:":"u/1f408.png",":cherry_blossom:":"u/1f338.png",":chicken:":"u/1f414.png",":chipmunk:":"u/1f43f.png",":cow:":"u/1f42e.png",":cow2:":"u/1f404.png",":crab:":"u/1f980.png",":cricket:":"u/1f997.png",":crocodile:":"u/1f40a.png",":deciduous_tree:":"u/1f333.png",":deer:":"u/1f98c.png",":dog:":"u/1f436.png",":dog2:":"u/1f415.png",":dolphin:":"u/1f42c.png",":dove:":"u/1f54a.png",":dragon:":"u/1f409.png",":dragon_face:":"u/1f432.png",":dromedary_camel:":"u/1f42a.png",":duck:":"u/1f986.png",":eagle:":"u/1f985.png",":ear_of_rice:":"u/1f33e.png",":elephant:":"u/1f418.png",":evergreen_tree:":"u/1f332.png",":fallen_leaf:":"u/1f342.png",":feet:":"u/1f43e.png",":fish:":"u/1f41f.png",":four_leaf_clover:":"u/1f340.png",":fox:":"u/1f98a.png",":frog:":"u/1f438.png",":giraffe:":"u/1f992.png",":goat:":"u/1f410.png",":gorilla:":"u/1f98d.png",":hamster:":"u/1f439.png",":hatched_chick:":"u/1f425.png",":hatching_chick:":"u/1f423.png",":hedgehog:":"u/1f994.png",":herb:":"u/1f33f.png",":hibiscus:":"u/1f33a.png",":horse:":"u/1f434.png",":koala:":"u/1f428.png",":leaves:":"u/1f343.png",":leopard:":"u/1f406.png",":lion_face:":"u/1f981.png",":lizard:":"u/1f98e.png",":maple_leaf:":"u/1f341.png",":monkey:":"u/1f412.png",":monkey_face:":"u/1f435.png",":mouse:":"u/1f42d.png",":mouse2:":"u/1f401.png",":octopus:":"u/1f419.png",":owl:":"u/1f989.png",":ox:":"u/1f402.png",":palm_tree:":"u/1f334.png",":panda_face:":"u/1f43c.png",":penguin:":"u/1f427.png",":pig:":"u/1f437.png",":pig2:":"u/1f416.png",":pig_nose:":"u/1f43d.png",":poodle:":"u/1f429.png",":rabbit:":"u/1f430.png",":rabbit2:":"u/1f407.png",":racehorse:":"u/1f40e.png",":ram:":"u/1f40f.png",":rat:":"u/1f400.png",":rhino:":"u/1f98f.png",":rooster:":"u/1f413.png",":rose:":"u/1f339.png",":rosette:":"u/1f3f5.png",":sauropod:":"u/1f995.png",":scorpion:":"u/1f982.png",":seedling:":"u/1f331.png",":shamrock:":"u/2618.png",":shark:":"u/1f988.png",":sheep:":"u/1f411.png",":shell:":"u/1f41a.png",":shrimp:":"u/1f990.png",":snail:":"u/1f40c.png",":snake:":"u/1f40d.png",":spider:":"u/1f577.png",":spider_web:":"u/1f578.png",":squid:":"u/1f991.png",":sunflower:":"u/1f33b.png",":t_rex:":"u/1f996.png",":tiger:":"u/1f42f.png",":tiger2:":"u/1f405.png",":tropical_fish:":"u/1f420.png",":tulip:":"u/1f337.png",":turkey:":"u/1f983.png",":turtle:":"u/1f422.png",":unicorn:":"u/1f984.png",":water_buffalo:":"u/1f403.png",":whale:":"u/1f433.png",":whale2:":"u/1f40b.png",":white_flower:":"u/1f4ae.png",":wilted_rose:":"u/1f940.png",":wolf:":"u/1f43a.png",":zebra:":"u/1f993.png",":checkered_flag:":"u/1f3c1.png",":crossed_flags:":"u/1f38c.png",":england:":"u/1f3f4-e0067-e0062-e0065-e006e-e0067-e007f.png",":flag_ac:":"u/1f1e6-1f1e8.png",":flag_ad:":"u/1f1e6-1f1e9.png",":flag_ae:":"u/1f1e6-1f1ea.png",":flag_af:":"u/1f1e6-1f1eb.png",":flag_ag:":"u/1f1e6-1f1ec.png",":flag_ai:":"u/1f1e6-1f1ee.png",":flag_al:":"u/1f1e6-1f1f1.png",":flag_am:":"u/1f1e6-1f1f2.png",":flag_ao:":"u/1f1e6-1f1f4.png",":flag_aq:":"u/1f1e6-1f1f6.png",":flag_ar:":"u/1f1e6-1f1f7.png",":flag_as:":"u/1f1e6-1f1f8.png",":flag_at:":"u/1f1e6-1f1f9.png",":flag_au:":"u/1f1e6-1f1fa.png",":flag_aw:":"u/1f1e6-1f1fc.png",":flag_ax:":"u/1f1e6-1f1fd.png",":flag_az:":"u/1f1e6-1f1ff.png",":flag_ba:":"u/1f1e7-1f1e6.png",":flag_bb:":"u/1f1e7-1f1e7.png",":flag_bd:":"u/1f1e7-1f1e9.png",":flag_be:":"u/1f1e7-1f1ea.png",":flag_bf:":"u/1f1e7-1f1eb.png",":flag_bg:":"u/1f1e7-1f1ec.png",":flag_bh:":"u/1f1e7-1f1ed.png",":flag_bi:":"u/1f1e7-1f1ee.png",":flag_bj:":"u/1f1e7-1f1ef.png",":flag_bl:":"u/1f1e7-1f1f1.png",":flag_black:":"u/1f3f4.png",":flag_bm:":"u/1f1e7-1f1f2.png",":flag_bn:":"u/1f1e7-1f1f3.png",":flag_bo:":"u/1f1e7-1f1f4.png",":flag_bq:":"u/1f1e7-1f1f6.png",":flag_br:":"u/1f1e7-1f1f7.png",":flag_bs:":"u/1f1e7-1f1f8.png",":flag_bt:":"u/1f1e7-1f1f9.png",":flag_bv:":"u/1f1e7-1f1fb.png",":flag_bw:":"u/1f1e7-1f1fc.png",":flag_by:":"u/1f1e7-1f1fe.png",":flag_bz:":"u/1f1e7-1f1ff.png",":flag_ca:":"u/1f1e8-1f1e6.png",":flag_cc:":"u/1f1e8-1f1e8.png",":flag_cd:":"u/1f1e8-1f1e9.png",":flag_cf:":"u/1f1e8-1f1eb.png",":flag_cg:":"u/1f1e8-1f1ec.png",":flag_ch:":"u/1f1e8-1f1ed.png",":flag_ci:":"u/1f1e8-1f1ee.png",":flag_ck:":"u/1f1e8-1f1f0.png",":flag_cl:":"u/1f1e8-1f1f1.png",":flag_cm:":"u/1f1e8-1f1f2.png",":flag_cn:":"u/1f1e8-1f1f3.png",":flag_co:":"u/1f1e8-1f1f4.png",":flag_cp:":"u/1f1e8-1f1f5.png",":flag_cr:":"u/1f1e8-1f1f7.png",":flag_cu:":"u/1f1e8-1f1fa.png",":flag_cv:":"u/1f1e8-1f1fb.png",":flag_cw:":"u/1f1e8-1f1fc.png",":flag_cx:":"u/1f1e8-1f1fd.png",":flag_cy:":"u/1f1e8-1f1fe.png",":flag_cz:":"u/1f1e8-1f1ff.png",":flag_de:":"u/1f1e9-1f1ea.png",":flag_dg:":"u/1f1e9-1f1ec.png",":flag_dj:":"u/1f1e9-1f1ef.png",":flag_dk:":"u/1f1e9-1f1f0.png",":flag_dm:":"u/1f1e9-1f1f2.png",":flag_do:":"u/1f1e9-1f1f4.png",":flag_dz:":"u/1f1e9-1f1ff.png",":flag_ea:":"u/1f1ea-1f1e6.png",":flag_ec:":"u/1f1ea-1f1e8.png",":flag_ee:":"u/1f1ea-1f1ea.png",":flag_eg:":"u/1f1ea-1f1ec.png",":flag_eh:":"u/1f1ea-1f1ed.png",":flag_er:":"u/1f1ea-1f1f7.png",":flag_es:":"u/1f1ea-1f1f8.png",":flag_et:":"u/1f1ea-1f1f9.png",":flag_eu:":"u/1f1ea-1f1fa.png",":flag_fi:":"u/1f1eb-1f1ee.png",":flag_fj:":"u/1f1eb-1f1ef.png",":flag_fk:":"u/1f1eb-1f1f0.png",":flag_fm:":"u/1f1eb-1f1f2.png",":flag_fo:":"u/1f1eb-1f1f4.png",":flag_fr:":"u/1f1eb-1f1f7.png",":flag_ga:":"u/1f1ec-1f1e6.png",":flag_gb:":"u/1f1ec-1f1e7.png",":flag_gd:":"u/1f1ec-1f1e9.png",":flag_ge:":"u/1f1ec-1f1ea.png",":flag_gf:":"u/1f1ec-1f1eb.png",":flag_gg:":"u/1f1ec-1f1ec.png",":flag_gh:":"u/1f1ec-1f1ed.png",":flag_gi:":"u/1f1ec-1f1ee.png",":flag_gl:":"u/1f1ec-1f1f1.png",":flag_gm:":"u/1f1ec-1f1f2.png",":flag_gn:":"u/1f1ec-1f1f3.png",":flag_gp:":"u/1f1ec-1f1f5.png",":flag_gq:":"u/1f1ec-1f1f6.png",":flag_gr:":"u/1f1ec-1f1f7.png",":flag_gs:":"u/1f1ec-1f1f8.png",":flag_gt:":"u/1f1ec-1f1f9.png",":flag_gu:":"u/1f1ec-1f1fa.png",":flag_gw:":"u/1f1ec-1f1fc.png",":flag_gy:":"u/1f1ec-1f1fe.png",":flag_hk:":"u/1f1ed-1f1f0.png",":flag_hm:":"u/1f1ed-1f1f2.png",":flag_hn:":"u/1f1ed-1f1f3.png",":flag_hr:":"u/1f1ed-1f1f7.png",":flag_ht:":"u/1f1ed-1f1f9.png",":flag_hu:":"u/1f1ed-1f1fa.png",":flag_ic:":"u/1f1ee-1f1e8.png",":flag_id:":"u/1f1ee-1f1e9.png",":flag_ie:":"u/1f1ee-1f1ea.png",":flag_il:":"u/1f1ee-1f1f1.png",":flag_im:":"u/1f1ee-1f1f2.png",":flag_in:":"u/1f1ee-1f1f3.png",":flag_io:":"u/1f1ee-1f1f4.png",":flag_iq:":"u/1f1ee-1f1f6.png",":flag_ir:":"u/1f1ee-1f1f7.png",":flag_is:":"u/1f1ee-1f1f8.png",":flag_it:":"u/1f1ee-1f1f9.png",":flag_je:":"u/1f1ef-1f1ea.png",":flag_jm:":"u/1f1ef-1f1f2.png",":flag_jo:":"u/1f1ef-1f1f4.png",":flag_jp:":"u/1f1ef-1f1f5.png",":flag_ke:":"u/1f1f0-1f1ea.png",":flag_kg:":"u/1f1f0-1f1ec.png",":flag_kh:":"u/1f1f0-1f1ed.png",":flag_ki:":"u/1f1f0-1f1ee.png",":flag_km:":"u/1f1f0-1f1f2.png",":flag_kn:":"u/1f1f0-1f1f3.png",":flag_kp:":"u/1f1f0-1f1f5.png",":flag_kr:":"u/1f1f0-1f1f7.png",":flag_kw:":"u/1f1f0-1f1fc.png",":flag_ky:":"u/1f1f0-1f1fe.png",":flag_kz:":"u/1f1f0-1f1ff.png",":flag_la:":"u/1f1f1-1f1e6.png",":flag_lb:":"u/1f1f1-1f1e7.png",":flag_lc:":"u/1f1f1-1f1e8.png",":flag_li:":"u/1f1f1-1f1ee.png",":flag_lk:":"u/1f1f1-1f1f0.png",":flag_lr:":"u/1f1f1-1f1f7.png",":flag_ls:":"u/1f1f1-1f1f8.png",":flag_lt:":"u/1f1f1-1f1f9.png",":flag_lu:":"u/1f1f1-1f1fa.png",":flag_lv:":"u/1f1f1-1f1fb.png",":flag_ly:":"u/1f1f1-1f1fe.png",":flag_ma:":"u/1f1f2-1f1e6.png",":flag_mc:":"u/1f1f2-1f1e8.png",":flag_md:":"u/1f1f2-1f1e9.png",":flag_me:":"u/1f1f2-1f1ea.png",":flag_mf:":"u/1f1f2-1f1eb.png",":flag_mg:":"u/1f1f2-1f1ec.png",":flag_mh:":"u/1f1f2-1f1ed.png",":flag_mk:":"u/1f1f2-1f1f0.png",":flag_ml:":"u/1f1f2-1f1f1.png",":flag_mm:":"u/1f1f2-1f1f2.png",":flag_mn:":"u/1f1f2-1f1f3.png",":flag_mo:":"u/1f1f2-1f1f4.png",":flag_mp:":"u/1f1f2-1f1f5.png",":flag_mq:":"u/1f1f2-1f1f6.png",":flag_mr:":"u/1f1f2-1f1f7.png",":flag_ms:":"u/1f1f2-1f1f8.png",":flag_mt:":"u/1f1f2-1f1f9.png",":flag_mu:":"u/1f1f2-1f1fa.png",":flag_mv:":"u/1f1f2-1f1fb.png",":flag_mw:":"u/1f1f2-1f1fc.png",":flag_mx:":"u/1f1f2-1f1fd.png",":flag_my:":"u/1f1f2-1f1fe.png",":flag_mz:":"u/1f1f2-1f1ff.png",":flag_na:":"u/1f1f3-1f1e6.png",":flag_nc:":"u/1f1f3-1f1e8.png",":flag_ne:":"u/1f1f3-1f1ea.png",":flag_nf:":"u/1f1f3-1f1eb.png",":flag_ng:":"u/1f1f3-1f1ec.png",":flag_ni:":"u/1f1f3-1f1ee.png",":flag_nl:":"u/1f1f3-1f1f1.png",":flag_no:":"u/1f1f3-1f1f4.png",":flag_np:":"u/1f1f3-1f1f5.png",":flag_nr:":"u/1f1f3-1f1f7.png",":flag_nu:":"u/1f1f3-1f1fa.png",":flag_nz:":"u/1f1f3-1f1ff.png",":flag_om:":"u/1f1f4-1f1f2.png",":flag_pa:":"u/1f1f5-1f1e6.png",":flag_pe:":"u/1f1f5-1f1ea.png",":flag_pf:":"u/1f1f5-1f1eb.png",":flag_pg:":"u/1f1f5-1f1ec.png",":flag_ph:":"u/1f1f5-1f1ed.png",":flag_pk:":"u/1f1f5-1f1f0.png",":flag_pl:":"u/1f1f5-1f1f1.png",":flag_pm:":"u/1f1f5-1f1f2.png",":flag_pn:":"u/1f1f5-1f1f3.png",":flag_pr:":"u/1f1f5-1f1f7.png",":flag_ps:":"u/1f1f5-1f1f8.png",":flag_pt:":"u/1f1f5-1f1f9.png",":flag_pw:":"u/1f1f5-1f1fc.png",":flag_py:":"u/1f1f5-1f1fe.png",":flag_qa:":"u/1f1f6-1f1e6.png",":flag_re:":"u/1f1f7-1f1ea.png",":flag_ro:":"u/1f1f7-1f1f4.png",":flag_rs:":"u/1f1f7-1f1f8.png",":flag_ru:":"u/1f1f7-1f1fa.png",":flag_rw:":"u/1f1f7-1f1fc.png",":flag_sa:":"u/1f1f8-1f1e6.png",":flag_sb:":"u/1f1f8-1f1e7.png",":flag_sc:":"u/1f1f8-1f1e8.png",":flag_sd:":"u/1f1f8-1f1e9.png",":flag_se:":"u/1f1f8-1f1ea.png",":flag_sg:":"u/1f1f8-1f1ec.png",":flag_sh:":"u/1f1f8-1f1ed.png",":flag_si:":"u/1f1f8-1f1ee.png",":flag_sj:":"u/1f1f8-1f1ef.png",":flag_sk:":"u/1f1f8-1f1f0.png",":flag_sl:":"u/1f1f8-1f1f1.png",":flag_sm:":"u/1f1f8-1f1f2.png",":flag_sn:":"u/1f1f8-1f1f3.png",":flag_so:":"u/1f1f8-1f1f4.png",":flag_sr:":"u/1f1f8-1f1f7.png",":flag_ss:":"u/1f1f8-1f1f8.png",":flag_st:":"u/1f1f8-1f1f9.png",":flag_sv:":"u/1f1f8-1f1fb.png",":flag_sx:":"u/1f1f8-1f1fd.png",":flag_sy:":"u/1f1f8-1f1fe.png",":flag_sz:":"u/1f1f8-1f1ff.png",":flag_ta:":"u/1f1f9-1f1e6.png",":flag_tc:":"u/1f1f9-1f1e8.png",":flag_td:":"u/1f1f9-1f1e9.png",":flag_tf:":"u/1f1f9-1f1eb.png",":flag_tg:":"u/1f1f9-1f1ec.png",":flag_th:":"u/1f1f9-1f1ed.png",":flag_tj:":"u/1f1f9-1f1ef.png",":flag_tk:":"u/1f1f9-1f1f0.png",":flag_tl:":"u/1f1f9-1f1f1.png",":flag_tm:":"u/1f1f9-1f1f2.png",":flag_tn:":"u/1f1f9-1f1f3.png",":flag_to:":"u/1f1f9-1f1f4.png",":flag_tr:":"u/1f1f9-1f1f7.png",":flag_tt:":"u/1f1f9-1f1f9.png",":flag_tv:":"u/1f1f9-1f1fb.png",":flag_tw:":"u/1f1f9-1f1fc.png",":flag_tz:":"u/1f1f9-1f1ff.png",":flag_ua:":"u/1f1fa-1f1e6.png",":flag_ug:":"u/1f1fa-1f1ec.png",":flag_um:":"u/1f1fa-1f1f2.png",":flag_us:":"u/1f1fa-1f1f8.png",":flag_uy:":"u/1f1fa-1f1fe.png",":flag_uz:":"u/1f1fa-1f1ff.png",":flag_va:":"u/1f1fb-1f1e6.png",":flag_vc:":"u/1f1fb-1f1e8.png",":flag_ve:":"u/1f1fb-1f1ea.png",":flag_vg:":"u/1f1fb-1f1ec.png",":flag_vi:":"u/1f1fb-1f1ee.png",":flag_vn:":"u/1f1fb-1f1f3.png",":flag_vu:":"u/1f1fb-1f1fa.png",":flag_wf:":"u/1f1fc-1f1eb.png",":flag_white:":"u/1f3f3.png",":flag_ws:":"u/1f1fc-1f1f8.png",":flag_xk:":"u/1f1fd-1f1f0.png",":flag_ye:":"u/1f1fe-1f1ea.png",":flag_yt:":"u/1f1fe-1f1f9.png",":flag_za:":"u/1f1ff-1f1e6.png",":flag_zm:":"u/1f1ff-1f1f2.png",":flag_zw:":"u/1f1ff-1f1fc.png",":rainbow_flag:":"u/1f3f3-1f308.png",":scotland:":"u/1f3f4-e0067-e0062-e0073-e0063-e0074-e007f.png",":triangular_flag_on_post:":"u/1f6a9.png",":united_nations:":"u/1f1fa-1f1f3.png",":wales:":"u/1f3f4-e0067-e0062-e0077-e006c-e0073-e007f.png"}}